
[
  {
    "attribute" : "links",
    "data" : {
"PE" : ["<a href='https://www.hpc-certification.org/wiki/skill-tree/pe/'>Online description</a>"],
"PE1" : ["<a href='https://www.hpc-certification.org/wiki/skill-tree/pe/1/'>Online description</a>"],
"PE3" : ["<a href='https://www.hpc-certification.org/wiki/skill-tree/pe/3/'>Online description</a>"],
"PE4" : ["<a href='https://www.hpc-certification.org/wiki/skill-tree/pe/4/'>Online description</a>"],
"PE4.1" : ["<a href='https://www.hpc-certification.org/wiki/skill-tree/pe/4/1/'>Online description</a>"],
"PE4.3" : ["<a href='https://www.hpc-certification.org/wiki/skill-tree/pe/4/3/'>Online description</a>"],
"PE4.2" : ["<a href='https://www.hpc-certification.org/wiki/skill-tree/pe/4/2/'>Online description</a>"],
"PE2" : ["<a href='https://www.hpc-certification.org/wiki/skill-tree/pe/2/'>Online description</a>"],
"PE2.1" : ["<a href='https://www.hpc-certification.org/wiki/skill-tree/pe/2/1/'>Online description</a>"],
"PE2.2" : ["<a href='https://www.hpc-certification.org/wiki/skill-tree/pe/2/2/'>Online description</a>"],
"PE5" : ["<a href='https://www.hpc-certification.org/wiki/skill-tree/pe/5/'>Online description</a>"],
"K" : ["<a href='https://www.hpc-certification.org/wiki/skill-tree/k/'>Online description</a>"],
"K1" : ["<a href='https://www.hpc-certification.org/wiki/skill-tree/k/1/'>Online description</a>"],
"K1.1" : ["<a href='https://www.hpc-certification.org/wiki/skill-tree/k/1/1/'>Online description</a>"],
"K1.3" : ["<a href='https://www.hpc-certification.org/wiki/skill-tree/k/1/3/'>Online description</a>"],
"K1.4" : ["<a href='https://www.hpc-certification.org/wiki/skill-tree/k/1/4/'>Online description</a>"],
"K1.2" : ["<a href='https://www.hpc-certification.org/wiki/skill-tree/k/1/2/'>Online description</a>"],
"K1.5" : ["<a href='https://www.hpc-certification.org/wiki/skill-tree/k/1/5/'>Online description</a>"],
"K3" : ["<a href='https://www.hpc-certification.org/wiki/skill-tree/k/3/'>Online description</a>"],
"K3.1" : ["<a href='https://www.hpc-certification.org/wiki/skill-tree/k/3/1/'>Online description</a>"],
"K3.3" : ["<a href='https://www.hpc-certification.org/wiki/skill-tree/k/3/3/'>Online description</a>"],
"K3.4" : ["<a href='https://www.hpc-certification.org/wiki/skill-tree/k/3/4/'>Online description</a>"],
"K3.2" : ["<a href='https://www.hpc-certification.org/wiki/skill-tree/k/3/2/'>Online description</a>"],
"K4" : ["<a href='https://www.hpc-certification.org/wiki/skill-tree/k/4/'>Online description</a>"],
"K4.1" : ["<a href='https://www.hpc-certification.org/wiki/skill-tree/k/4/1/'>Online description</a>"],
"K4.2" : ["<a href='https://www.hpc-certification.org/wiki/skill-tree/k/4/2/'>Online description</a>"],
"K2" : ["<a href='https://www.hpc-certification.org/wiki/skill-tree/k/2/'>Online description</a>"],
"K2.1" : ["<a href='https://www.hpc-certification.org/wiki/skill-tree/k/2/1/'>Online description</a>"],
"K2.2" : ["<a href='https://www.hpc-certification.org/wiki/skill-tree/k/2/2/'>Online description</a>"],
"K5" : ["<a href='https://www.hpc-certification.org/wiki/skill-tree/k/5/'>Online description</a>"],
"SD" : ["<a href='https://www.hpc-certification.org/wiki/skill-tree/sd/'>Online description</a>"],
"SD1" : ["<a href='https://www.hpc-certification.org/wiki/skill-tree/sd/1/'>Online description</a>"],
"SD1.1" : ["<a href='https://www.hpc-certification.org/wiki/skill-tree/sd/1/1/'>Online description</a>"],
"SD1.3" : ["<a href='https://www.hpc-certification.org/wiki/skill-tree/sd/1/3/'>Online description</a>"],
"SD1.2" : ["<a href='https://www.hpc-certification.org/wiki/skill-tree/sd/1/2/'>Online description</a>"],
"SD1.2.1" : ["<a href='https://www.hpc-certification.org/wiki/skill-tree/sd/1/2/1/'>Online description</a>"],
"SD1.2.3" : ["<a href='https://www.hpc-certification.org/wiki/skill-tree/sd/1/2/3/'>Online description</a>"],
"SD1.2.4" : ["<a href='https://www.hpc-certification.org/wiki/skill-tree/sd/1/2/4/'>Online description</a>"],
"SD1.2.2" : ["<a href='https://www.hpc-certification.org/wiki/skill-tree/sd/1/2/2/'>Online description</a>"],
"SD1.2.5" : ["<a href='https://www.hpc-certification.org/wiki/skill-tree/sd/1/2/5/'>Online description</a>"],
"SD6" : ["<a href='https://www.hpc-certification.org/wiki/skill-tree/sd/6/'>Online description</a>"],
"SD6.1" : ["<a href='https://www.hpc-certification.org/wiki/skill-tree/sd/6/1/'>Online description</a>"],
"SD6.3" : ["<a href='https://www.hpc-certification.org/wiki/skill-tree/sd/6/3/'>Online description</a>"],
"SD6.2" : ["<a href='https://www.hpc-certification.org/wiki/skill-tree/sd/6/2/'>Online description</a>"],
"SD3" : ["<a href='https://www.hpc-certification.org/wiki/skill-tree/sd/3/'>Online description</a>"],
"SD3.1" : ["<a href='https://www.hpc-certification.org/wiki/skill-tree/sd/3/1/'>Online description</a>"],
"SD3.3" : ["<a href='https://www.hpc-certification.org/wiki/skill-tree/sd/3/3/'>Online description</a>"],
"SD3.4" : ["<a href='https://www.hpc-certification.org/wiki/skill-tree/sd/3/4/'>Online description</a>"],
"SD3.2" : ["<a href='https://www.hpc-certification.org/wiki/skill-tree/sd/3/2/'>Online description</a>"],
"SD3.5" : ["<a href='https://www.hpc-certification.org/wiki/skill-tree/sd/3/5/'>Online description</a>"],
"SD4" : ["<a href='https://www.hpc-certification.org/wiki/skill-tree/sd/4/'>Online description</a>"],
"SD4.1" : ["<a href='https://www.hpc-certification.org/wiki/skill-tree/sd/4/1/'>Online description</a>"],
"SD4.3" : ["<a href='https://www.hpc-certification.org/wiki/skill-tree/sd/4/3/'>Online description</a>"],
"SD4.2" : ["<a href='https://www.hpc-certification.org/wiki/skill-tree/sd/4/2/'>Online description</a>"],
"SD2" : ["<a href='https://www.hpc-certification.org/wiki/skill-tree/sd/2/'>Online description</a>"],
"SD2.1" : ["<a href='https://www.hpc-certification.org/wiki/skill-tree/sd/2/1/'>Online description</a>"],
"SD2.6" : ["<a href='https://www.hpc-certification.org/wiki/skill-tree/sd/2/6/'>Online description</a>"],
"SD2.3" : ["<a href='https://www.hpc-certification.org/wiki/skill-tree/sd/2/3/'>Online description</a>"],
"SD2.4" : ["<a href='https://www.hpc-certification.org/wiki/skill-tree/sd/2/4/'>Online description</a>"],
"SD2.2" : ["<a href='https://www.hpc-certification.org/wiki/skill-tree/sd/2/2/'>Online description</a>"],
"SD2.7" : ["<a href='https://www.hpc-certification.org/wiki/skill-tree/sd/2/7/'>Online description</a>"],
"SD2.5" : ["<a href='https://www.hpc-certification.org/wiki/skill-tree/sd/2/5/'>Online description</a>"],
"SD2.8" : ["<a href='https://www.hpc-certification.org/wiki/skill-tree/sd/2/8/'>Online description</a>"],
"SD7" : ["<a href='https://www.hpc-certification.org/wiki/skill-tree/sd/7/'>Online description</a>"],
"SD7.1" : ["<a href='https://www.hpc-certification.org/wiki/skill-tree/sd/7/1/'>Online description</a>"],
"SD7.3" : ["<a href='https://www.hpc-certification.org/wiki/skill-tree/sd/7/3/'>Online description</a>"],
"SD7.4" : ["<a href='https://www.hpc-certification.org/wiki/skill-tree/sd/7/4/'>Online description</a>"],
"SD7.2" : ["<a href='https://www.hpc-certification.org/wiki/skill-tree/sd/7/2/'>Online description</a>"],
"SD5" : ["<a href='https://www.hpc-certification.org/wiki/skill-tree/sd/5/'>Online description</a>"],
"SD5.1" : ["<a href='https://www.hpc-certification.org/wiki/skill-tree/sd/5/1/'>Online description</a>"],
"SD5.3" : ["<a href='https://www.hpc-certification.org/wiki/skill-tree/sd/5/3/'>Online description</a>"],
"SD5.4" : ["<a href='https://www.hpc-certification.org/wiki/skill-tree/sd/5/4/'>Online description</a>"],
"SD5.2" : ["<a href='https://www.hpc-certification.org/wiki/skill-tree/sd/5/2/'>Online description</a>"],
"ADM" : ["<a href='https://www.hpc-certification.org/wiki/skill-tree/adm/'>Online description</a>"],
"ADM1" : ["<a href='https://www.hpc-certification.org/wiki/skill-tree/adm/1/'>Online description</a>"],
"ADM3" : ["<a href='https://www.hpc-certification.org/wiki/skill-tree/adm/3/'>Online description</a>"],
"ADM2" : ["<a href='https://www.hpc-certification.org/wiki/skill-tree/adm/2/'>Online description</a>"],
"USE" : ["<a href='https://www.hpc-certification.org/wiki/skill-tree/use/'>Online description</a>"],
"USE1" : ["<a href='https://www.hpc-certification.org/wiki/skill-tree/use/1/'>Online description</a>"],
"USE1.1" : ["<a href='https://www.hpc-certification.org/wiki/skill-tree/use/1/1/'>Online description</a>"],
"USE1.3" : ["<a href='https://www.hpc-certification.org/wiki/skill-tree/use/1/3/'>Online description</a>"],
"USE1.4" : ["<a href='https://www.hpc-certification.org/wiki/skill-tree/use/1/4/'>Online description</a>"],
"USE1.4.1" : ["<a href='https://www.hpc-certification.org/wiki/skill-tree/use/1/4/1/'>Online description</a>"],
"USE1.4.3" : ["<a href='https://www.hpc-certification.org/wiki/skill-tree/use/1/4/3/'>Online description</a>"],
"USE1.4.2" : ["<a href='https://www.hpc-certification.org/wiki/skill-tree/use/1/4/2/'>Online description</a>"],
"USE1.2" : ["<a href='https://www.hpc-certification.org/wiki/skill-tree/use/1/2/'>Online description</a>"],
"USE1.5" : ["<a href='https://www.hpc-certification.org/wiki/skill-tree/use/1/5/'>Online description</a>"],
"USE6" : ["<a href='https://www.hpc-certification.org/wiki/skill-tree/use/6/'>Online description</a>"],
"USE3" : ["<a href='https://www.hpc-certification.org/wiki/skill-tree/use/3/'>Online description</a>"],
"USE4" : ["<a href='https://www.hpc-certification.org/wiki/skill-tree/use/4/'>Online description</a>"],
"USE2" : ["<a href='https://www.hpc-certification.org/wiki/skill-tree/use/2/'>Online description</a>"],
"USE5" : ["<a href='https://www.hpc-certification.org/wiki/skill-tree/use/5/'>Online description</a>"],
"BDA" : ["<a href='https://www.hpc-certification.org/wiki/skill-tree/bda/'>Online description</a>"],
"BDA1" : ["<a href='https://www.hpc-certification.org/wiki/skill-tree/bda/1/'>Online description</a>"],
"BDA3" : ["<a href='https://www.hpc-certification.org/wiki/skill-tree/bda/3/'>Online description</a>"],
"BDA2" : ["<a href='https://www.hpc-certification.org/wiki/skill-tree/bda/2/'>Online description</a>"]    }
  }
]
